{
	"$schema": "http://schema.management.azure.com/schemas/2015-01-01/deploymentTemplate.json#",
	"contentVersion": "1.0.0.0",
	"parameters": {
		"factoryName": {
			"type": "string",
			"metadata": "Data Factory name",
			"defaultValue": "adfdemostevedf"
		},
		"tr_storageevent_demo_properties_typeProperties_scope": {
			"type": "string",
			"defaultValue": "/subscriptions/8632adbe-0938-47d7-8280-1c9f4785d918/resourceGroups/ADF-demo/providers/Microsoft.Storage/storageAccounts/adfdemostevea"
		}
	},
	"variables": {
		"factoryId": "[concat('Microsoft.DataFactory/factories/', parameters('factoryName'))]"
	},
	"resources": [
		{
			"name": "[concat(parameters('factoryName'), '/tr_demo')]",
			"type": "Microsoft.DataFactory/factories/triggers",
			"apiVersion": "2018-06-01",
			"properties": {
				"annotations": [],
				"runtimeState": "Stopped",
				"pipelines": [],
				"type": "ScheduleTrigger",
				"typeProperties": {
					"recurrence": {
						"frequency": "Day",
						"interval": 1,
						"startTime": "2024-11-09T16:16:00",
						"timeZone": "GMT Standard Time",
						"schedule": {
							"minutes": [
								30
							],
							"hours": [
								16
							]
						}
					}
				}
			},
			"dependsOn": []
		},
		{
			"name": "[concat(parameters('factoryName'), '/tr_schedule_demo')]",
			"type": "Microsoft.DataFactory/factories/triggers",
			"apiVersion": "2018-06-01",
			"properties": {
				"annotations": [],
				"runtimeState": "Stopped",
				"pipelines": [],
				"type": "ScheduleTrigger",
				"typeProperties": {
					"recurrence": {
						"frequency": "Minute",
						"interval": 5,
						"startTime": "2024-11-19T12:09:00",
						"timeZone": "GMT Standard Time"
					}
				}
			},
			"dependsOn": []
		},
		{
			"name": "[concat(parameters('factoryName'), '/tr_storageevent_demo')]",
			"type": "Microsoft.DataFactory/factories/triggers",
			"apiVersion": "2018-06-01",
			"properties": {
				"annotations": [],
				"runtimeState": "Stopped",
				"pipelines": [],
				"type": "BlobEventsTrigger",
				"typeProperties": {
					"blobPathBeginsWith": "/storageeventtrigger/blobs/",
					"ignoreEmptyBlobs": true,
					"scope": "[parameters('tr_storageevent_demo_properties_typeProperties_scope')]",
					"events": [
						"Microsoft.Storage.BlobCreated"
					]
				}
			},
			"dependsOn": []
		},
		{
			"name": "[concat(parameters('factoryName'), '/trigger1')]",
			"type": "Microsoft.DataFactory/factories/triggers",
			"apiVersion": "2018-06-01",
			"properties": {
				"annotations": [],
				"runtimeState": "Stopped",
				"pipelines": [],
				"type": "ScheduleTrigger",
				"typeProperties": {
					"recurrence": {
						"frequency": "Minute",
						"interval": 15,
						"startTime": "2024-11-19T12:06:00",
						"timeZone": "GMT Standard Time"
					}
				}
			},
			"dependsOn": []
		},
		{
			"name": "[concat(parameters('factoryName'), '/self-hosted-ir')]",
			"type": "Microsoft.DataFactory/factories/integrationRuntimes",
			"apiVersion": "2018-06-01",
			"properties": {
				"type": "SelfHosted",
				"typeProperties": {}
			},
			"dependsOn": []
		},
		{
			"name": "[concat(parameters('factoryName'), '/pl_execute_activity_demo')]",
			"type": "Microsoft.DataFactory/factories/pipelines",
			"apiVersion": "2018-06-01",
			"properties": {
				"activities": [
					{
						"name": "Execute Pipeline1",
						"type": "ExecutePipeline",
						"dependsOn": [],
						"policy": {
							"secureInput": false
						},
						"userProperties": [],
						"typeProperties": {
							"pipeline": {
								"referenceName": "pl_execute_activity_demo_child1",
								"type": "PipelineReference"
							},
							"waitOnCompletion": true,
							"parameters": {}
						}
					},
					{
						"name": "Execute Pipeline2",
						"type": "ExecutePipeline",
						"dependsOn": [
							{
								"activity": "Execute Pipeline1",
								"dependencyConditions": [
									"Succeeded"
								]
							}
						],
						"policy": {
							"secureInput": false
						},
						"userProperties": [],
						"typeProperties": {
							"pipeline": {
								"referenceName": "pl_execute_activity_demo_child2",
								"type": "PipelineReference"
							},
							"waitOnCompletion": true,
							"parameters": {}
						}
					}
				],
				"policy": {
					"elapsedTimeMetric": {}
				},
				"annotations": [],
				"lastPublishTime": "2024-11-12T20:01:14Z"
			},
			"dependsOn": []
		},
		{
			"name": "[concat(parameters('factoryName'), '/pl_rw4_audit_pipeline')]",
			"type": "Microsoft.DataFactory/factories/pipelines",
			"apiVersion": "2018-06-01",
			"properties": {
				"activities": [
					{
						"name": "Wait1",
						"type": "Wait",
						"dependsOn": [],
						"userProperties": [],
						"typeProperties": {
							"waitTimeInSeconds": 5
						}
					},
					{
						"name": "Stored procedure1",
						"type": "SqlServerStoredProcedure",
						"dependsOn": [
							{
								"activity": "Wait1",
								"dependencyConditions": [
									"Succeeded"
								]
							}
						],
						"policy": {
							"timeout": "0.12:00:00",
							"retry": 0,
							"retryIntervalInSeconds": 30,
							"secureOutput": false,
							"secureInput": false
						},
						"userProperties": [],
						"typeProperties": {
							"storedProcedureName": "[[dbo].[audit_rw_4_stp]",
							"storedProcedureParameters": {
								"message": {
									"value": {
										"value": "@concat('pipeline name:', pipeline().Pipeline)",
										"type": "Expression"
									},
									"type": "String"
								}
							}
						},
						"linkedServiceName": {
							"referenceName": "az_sql_1",
							"type": "LinkedServiceReference"
						}
					}
				],
				"policy": {
					"elapsedTimeMetric": {}
				},
				"annotations": [],
				"lastPublishTime": "2024-11-12T18:21:36Z"
			},
			"dependsOn": []
		},
		{
			"name": "[concat(parameters('factoryName'), '/pl_stored_procedure_demo')]",
			"type": "Microsoft.DataFactory/factories/pipelines",
			"apiVersion": "2018-06-01",
			"properties": {
				"activities": [
					{
						"name": "Stored procedure1",
						"type": "SqlServerStoredProcedure",
						"dependsOn": [],
						"policy": {
							"timeout": "0.12:00:00",
							"retry": 0,
							"retryIntervalInSeconds": 30,
							"secureOutput": false,
							"secureInput": false
						},
						"userProperties": [],
						"typeProperties": {
							"storedProcedureName": "[[dbo].[sp_delete_dept]",
							"storedProcedureParameters": {
								"p_dept_name": {
									"value": {
										"value": "@pipeline().parameters.deptName",
										"type": "Expression"
									},
									"type": "String"
								}
							}
						},
						"linkedServiceName": {
							"referenceName": "az_sql_1",
							"type": "LinkedServiceReference"
						}
					}
				],
				"policy": {
					"elapsedTimeMetric": {}
				},
				"parameters": {
					"deptName": {
						"type": "string",
						"defaultValue": "Steve"
					}
				},
				"annotations": [],
				"lastPublishTime": "2024-11-12T17:43:42Z"
			},
			"dependsOn": []
		},
		{
			"name": "[concat(parameters('factoryName'), '/AzureSqlTable1')]",
			"type": "Microsoft.DataFactory/factories/datasets",
			"apiVersion": "2018-06-01",
			"properties": {
				"linkedServiceName": {
					"referenceName": "az_sql_1",
					"type": "LinkedServiceReference"
				},
				"annotations": [],
				"type": "AzureSqlTable",
				"schema": [
					{
						"name": "Customer",
						"type": "varchar"
					},
					{
						"name": "Gender",
						"type": "varchar"
					},
					{
						"name": "Product_code",
						"type": "varchar"
					},
					{
						"name": "Price",
						"type": "varchar"
					},
					{
						"name": "Filename",
						"type": "varchar"
					}
				],
				"typeProperties": {
					"schema": "dbo",
					"table": "Sales"
				}
			},
			"dependsOn": []
		},
		{
			"name": "[concat(parameters('factoryName'), '/AzureSqlTable4')]",
			"type": "Microsoft.DataFactory/factories/datasets",
			"apiVersion": "2018-06-01",
			"properties": {
				"linkedServiceName": {
					"referenceName": "az_sql_1",
					"type": "LinkedServiceReference"
				},
				"annotations": [],
				"type": "AzureSqlTable",
				"schema": [
					{
						"name": "Dept_id",
						"type": "int",
						"precision": 10
					},
					{
						"name": "Dept_Name",
						"type": "varchar"
					}
				],
				"typeProperties": {
					"schema": "dbo",
					"table": "dept"
				}
			},
			"dependsOn": []
		},
		{
			"name": "[concat(parameters('factoryName'), '/AzureSqlTable5')]",
			"type": "Microsoft.DataFactory/factories/datasets",
			"apiVersion": "2018-06-01",
			"properties": {
				"linkedServiceName": {
					"referenceName": "az_sql_1",
					"type": "LinkedServiceReference"
				},
				"annotations": [],
				"type": "AzureSqlTable",
				"schema": [
					{
						"name": "Emp_key",
						"type": "int",
						"precision": 10
					},
					{
						"name": "Emp_id",
						"type": "int",
						"precision": 10
					},
					{
						"name": "Name",
						"type": "varchar"
					},
					{
						"name": "Gender",
						"type": "varchar"
					},
					{
						"name": "Salary",
						"type": "int",
						"precision": 10
					},
					{
						"name": "Dept_id",
						"type": "int",
						"precision": 10
					}
				],
				"typeProperties": {
					"schema": "dbo",
					"table": "employees_tbl"
				}
			},
			"dependsOn": []
		},
		{
			"name": "[concat(parameters('factoryName'), '/Binary1')]",
			"type": "Microsoft.DataFactory/factories/datasets",
			"apiVersion": "2018-06-01",
			"properties": {
				"linkedServiceName": {
					"referenceName": "ls_adfdemostevedlg",
					"type": "LinkedServiceReference"
				},
				"annotations": [],
				"type": "Binary",
				"typeProperties": {
					"location": {
						"type": "AzureBlobFSLocation",
						"fileName": "Sales_04262022.csv",
						"folderPath": "delete1",
						"fileSystem": "deletedemo"
					}
				}
			},
			"dependsOn": []
		},
		{
			"name": "[concat(parameters('factoryName'), '/DelimitedText1')]",
			"type": "Microsoft.DataFactory/factories/datasets",
			"apiVersion": "2018-06-01",
			"properties": {
				"linkedServiceName": {
					"referenceName": "ls_azblob_adfdemostevea",
					"type": "LinkedServiceReference"
				},
				"annotations": [],
				"type": "DelimitedText",
				"typeProperties": {
					"location": {
						"type": "AzureBlobStorageLocation",
						"container": "restoutput"
					},
					"columnDelimiter": ",",
					"escapeChar": "\\",
					"firstRowAsHeader": true,
					"quoteChar": "\""
				},
				"schema": []
			},
			"dependsOn": []
		},
		{
			"name": "[concat(parameters('factoryName'), '/DelimitedText2')]",
			"type": "Microsoft.DataFactory/factories/datasets",
			"apiVersion": "2018-06-01",
			"properties": {
				"linkedServiceName": {
					"referenceName": "ls_azblob_adfdemostevea",
					"type": "LinkedServiceReference"
				},
				"annotations": [],
				"type": "DelimitedText",
				"typeProperties": {
					"location": {
						"type": "AzureBlobStorageLocation",
						"fileName": "demo_param.csv",
						"container": "demo"
					},
					"columnDelimiter": ",",
					"escapeChar": "\\",
					"firstRowAsHeader": true,
					"quoteChar": "\""
				},
				"schema": []
			},
			"dependsOn": []
		},
		{
			"name": "[concat(parameters('factoryName'), '/DelimitedText3')]",
			"type": "Microsoft.DataFactory/factories/datasets",
			"apiVersion": "2018-06-01",
			"properties": {
				"linkedServiceName": {
					"referenceName": "ls_adfdemostevedlg",
					"type": "LinkedServiceReference"
				},
				"annotations": [],
				"type": "DelimitedText",
				"typeProperties": {
					"location": {
						"type": "AzureBlobFSLocation",
						"fileSystem": "output"
					},
					"columnDelimiter": ",",
					"escapeChar": "\\",
					"firstRowAsHeader": true,
					"quoteChar": "\""
				},
				"schema": [
					{
						"name": "Customer",
						"type": "String"
					},
					{
						"name": "Gender",
						"type": "String"
					},
					{
						"name": "Product_code",
						"type": "String"
					},
					{
						"name": "Price",
						"type": "String"
					}
				]
			},
			"dependsOn": []
		},
		{
			"name": "[concat(parameters('factoryName'), '/DelimitedText4')]",
			"type": "Microsoft.DataFactory/factories/datasets",
			"apiVersion": "2018-06-01",
			"properties": {
				"linkedServiceName": {
					"referenceName": "ls_azblob_adfdemostevea",
					"type": "LinkedServiceReference"
				},
				"annotations": [],
				"type": "DelimitedText",
				"typeProperties": {
					"location": {
						"type": "AzureBlobStorageLocation",
						"fileName": "*.*",
						"container": "input2"
					},
					"columnDelimiter": ",",
					"escapeChar": "\\",
					"firstRowAsHeader": true,
					"quoteChar": "\""
				},
				"schema": [
					{
						"name": "Customer",
						"type": "String"
					},
					{
						"name": "Gender",
						"type": "String"
					},
					{
						"name": "Product_code",
						"type": "String"
					},
					{
						"name": "Price",
						"type": "String"
					}
				]
			},
			"dependsOn": []
		},
		{
			"name": "[concat(parameters('factoryName'), '/DelimitedText5')]",
			"type": "Microsoft.DataFactory/factories/datasets",
			"apiVersion": "2018-06-01",
			"properties": {
				"linkedServiceName": {
					"referenceName": "ls_adfdemostevedlg",
					"type": "LinkedServiceReference"
				},
				"annotations": [],
				"type": "DelimitedText",
				"typeProperties": {
					"location": {
						"type": "AzureBlobFSLocation",
						"fileSystem": "output"
					},
					"columnDelimiter": ",",
					"escapeChar": "\\",
					"firstRowAsHeader": true,
					"quoteChar": "\""
				},
				"schema": [
					{
						"name": "Customer",
						"type": "String"
					},
					{
						"name": "Gender",
						"type": "String"
					},
					{
						"name": "Product_code",
						"type": "String"
					},
					{
						"name": "Price",
						"type": "String"
					}
				]
			},
			"dependsOn": []
		},
		{
			"name": "[concat(parameters('factoryName'), '/DelimitedText6')]",
			"type": "Microsoft.DataFactory/factories/datasets",
			"apiVersion": "2018-06-01",
			"properties": {
				"linkedServiceName": {
					"referenceName": "ls_azblob_adfdemostevea",
					"type": "LinkedServiceReference"
				},
				"annotations": [],
				"type": "DelimitedText",
				"typeProperties": {
					"location": {
						"type": "AzureBlobStorageLocation",
						"fileName": "HumanResources.Employee.txt",
						"container": "demo"
					},
					"columnDelimiter": ",",
					"escapeChar": "\\",
					"firstRowAsHeader": true,
					"quoteChar": "\""
				},
				"schema": [
					{
						"name": "BusinessEntityID",
						"type": "String"
					},
					{
						"name": "NationalIDNumber",
						"type": "String"
					},
					{
						"name": "LoginID",
						"type": "String"
					},
					{
						"name": "OrganizationNode",
						"type": "String"
					},
					{
						"name": "OrganizationLevel",
						"type": "String"
					},
					{
						"name": "JobTitle",
						"type": "String"
					},
					{
						"name": "BirthDate",
						"type": "String"
					},
					{
						"name": "MaritalStatus",
						"type": "String"
					},
					{
						"name": "Gender",
						"type": "String"
					},
					{
						"name": "HireDate",
						"type": "String"
					},
					{
						"name": "SalariedFlag",
						"type": "String"
					},
					{
						"name": "VacationHours",
						"type": "String"
					},
					{
						"name": "SickLeaveHours",
						"type": "String"
					},
					{
						"name": "CurrentFlag",
						"type": "String"
					},
					{
						"name": "rowguid",
						"type": "String"
					},
					{
						"name": "ModifiedDate",
						"type": "String"
					}
				]
			},
			"dependsOn": []
		},
		{
			"name": "[concat(parameters('factoryName'), '/DelimitedText7')]",
			"type": "Microsoft.DataFactory/factories/datasets",
			"apiVersion": "2018-06-01",
			"properties": {
				"linkedServiceName": {
					"referenceName": "ls_azblob_adfdemostevea",
					"type": "LinkedServiceReference"
				},
				"annotations": [],
				"type": "DelimitedText",
				"typeProperties": {
					"location": {
						"type": "AzureBlobStorageLocation",
						"fileName": "abcd.csv",
						"container": "validation-input"
					},
					"columnDelimiter": ",",
					"escapeChar": "\\",
					"firstRowAsHeader": true,
					"quoteChar": "\""
				},
				"schema": []
			},
			"dependsOn": []
		},
		{
			"name": "[concat(parameters('factoryName'), '/DelimitedText8')]",
			"type": "Microsoft.DataFactory/factories/datasets",
			"apiVersion": "2018-06-01",
			"properties": {
				"linkedServiceName": {
					"referenceName": "ls_azblob_adfdemostevea",
					"type": "LinkedServiceReference"
				},
				"annotations": [],
				"type": "DelimitedText",
				"typeProperties": {
					"location": {
						"type": "AzureBlobStorageLocation",
						"fileName": "abcd.csv",
						"container": "validation-input"
					},
					"columnDelimiter": ",",
					"escapeChar": "\\",
					"firstRowAsHeader": true,
					"quoteChar": "\""
				},
				"schema": []
			},
			"dependsOn": []
		}
	]
}